cachelm/__init__.py
cachelm/py.typed
cachelm/adaptors/__init__.py
cachelm/adaptors/adaptor.py
cachelm/adaptors/openai/__init__.py
cachelm/adaptors/openai/async_openai.py
cachelm/adaptors/openai/sync_openai.py
cachelm/databases/__init__.py
cachelm/databases/chroma.py
cachelm/databases/clickhouse.py
cachelm/databases/database.py
cachelm/databases/qdrant.py
cachelm/databases/redisvl.py
cachelm/middlewares/deduper.py
cachelm/middlewares/middleware.py
cachelm/middlewares/replacer.py
cachelm/middlewares/skipper.py
cachelm/utils/aggregator.py
cachelm/utils/async_wrap.py
cachelm/utils/chat_history.py
cachelm/vectorizers/__init__.py
cachelm/vectorizers/chroma.py
cachelm/vectorizers/fastembed.py
cachelm/vectorizers/redisvl.py
cachelm/vectorizers/vectorizer.py
cachelm-0.5.11.dist-info/METADATA
cachelm-0.5.11.dist-info/WHEEL
cachelm-0.5.11.dist-info/licenses/LICENCE.md
cachelm-0.5.11.dist-info/RECORD
