Metadata-Version: 2.4
Name: cachelm
Version: 0.5.11
Summary: A caching library for LLMs
Project-URL: Repository, https://github.com/devanmolsharma/cachelm
Author-email: Anmol Sharma <keepupsharma@gmail.com>
License-File: LICENCE.md
Requires-Python: >=3.10
Requires-Dist: dotenv>=0.9.9
Requires-Dist: loguru>=0.7.3
Requires-Dist: openai>=1.70.0
Provides-Extra: chroma
Requires-Dist: chromadb>=1.0.9; extra == 'chroma'
Requires-Dist: text2vec>=1.3.5; extra == 'chroma'
Provides-Extra: clickhouse
Requires-Dist: clickhouse-connect>=0.8.17; extra == 'clickhouse'
Provides-Extra: fastembed
Requires-Dist: fastembed>=0.7.0; extra == 'fastembed'
Provides-Extra: qdrant
Requires-Dist: qdrant-client>=1.0.0; extra == 'qdrant'
Provides-Extra: redis
Requires-Dist: redisvl>=0.6.0; extra == 'redis'
Requires-Dist: sentence-transformers>=4.1.0; extra == 'redis'
Provides-Extra: test
Requires-Dist: chromadb>=1.0.9; extra == 'test'
Requires-Dist: clickhouse-connect>=0.8.17; extra == 'test'
Requires-Dist: fastembed>=0.7.0; extra == 'test'
Requires-Dist: redisvl>=0.6.0; extra == 'test'
Requires-Dist: sentence-transformers>=4.1.0; extra == 'test'
Requires-Dist: text2vec>=1.3.5; extra == 'test'
